{"_id":{"$oid":"5ca371af004b3837e0bff901"},"title":"Horus Rising","content":"","banner":"","user_id":{"$oid":"5ca370040f4eab2e104901e8"},"__v":0}
{"_id":{"$oid":"5ca371af004b3837e0bff902"},"title":"Black Legion","content":"","banner":"","user_id":{"$oid":"5ca370aa0f4eab2e104901e9"},"__v":0}
{"_id":{"$oid":"5ca371af004b3837e0bff903"},"title":"Talon of Horus","content":"","banner":"","user_id":{"$oid":"5ca370aa0f4eab2e104901e9"},"__v":0}
{"_id":{"$oid":"5ca371af004b3837e0bff904"},"title":"Ahriman","content":"","banner":"","user_id":{"$oid":"5ca370c30f4eab2e104901ea"},"__v":0}
{"_id":{"$oid":"5ca371af004b3837e0bff905"},"title":"Brothers of the Snake","content":"","banner":"","user_id":{"$oid":"5ca370040f4eab2e104901e8"},"__v":0}
{"_id":{"$oid":"5ca371af004b3837e0bff906"},"title":"Dark Imperium","content":"","banner":"","user_id":{"$oid":"5ca370db0f4eab2e104901eb"},"__v":0}
{"_id":{"$oid":"5ca371af004b3837e0bff907"},"title":"Angels of Darkness","content":"","banner":"","user_id":{"$oid":"5ca370f50f4eab2e104901ec"},"__v":0}
{"_id":{"$oid":"5ca371af004b3837e0bff908"},"title":"Soul Drinkers","content":"","banner":"","user_id":{"$oid":"5ca371120f4eab2e104901ed"},"__v":0}
